[{"symbol": "27009", "name": "JP-GEG @EC2609B", "lastDone": 0.09, "changePercent": 5.88, "volume": 21550000, "strikePrice": 0.09, "expiryDate": "2026-09-11", "type": "call", "premium": 36.03, "leverage": 39.8}, {"symbol": "24067", "name": "BI-GEG @EP2606A", "lastDone": 0.149, "changePercent": -8.59, "volume": 18600000, "strikePrice": 0.149, "expiryDate": "2026-06-15", "type": "put", "premium": 14.03, "leverage": 24.0}, {"symbol": "27145", "name": "BI-GEG @EC2609A", "lastDone": 0.082, "changePercent": 10.81, "volume": 6200000, "strikePrice": 0.082, "expiryDate": "2026-09-04", "type": "call", "premium": 35.86, "leverage": 43.6}, {"symbol": "26482", "name": "HS-GEG @EC2609A", "lastDone": 0.033, "changePercent": 10.0, "volume": 5940000, "strikePrice": 0.033, "expiryDate": "2026-09-18", "type": "call", "premium": 59.75, "leverage": 108.4}, {"symbol": "22160", "name": "BP-GEG @EP2605A", "lastDone": 0.049, "changePercent": -16.95, "volume": 5460000, "strikePrice": 0.049, "expiryDate": "2026-05-19", "type": "put", "premium": 19.66, "leverage": 146.0}, {"symbol": "27217", "name": "HS-GEG @EC2609B", "lastDone": 0.086, "changePercent": 8.86, "volume": 3900000, "strikePrice": 0.086, "expiryDate": "2026-09-04", "type": "call", "premium": 35.97, "leverage": 41.6}, {"symbol": "21873", "name": "HU-GEG @EP2605A", "lastDone": 0.048, "changePercent": -15.79, "volume": 2850000, "strikePrice": 0.048, "expiryDate": "2026-05-27", "type": "put", "premium": 19.62, "leverage": 149.1}, {"symbol": "26135", "name": "MB-GEG @EC2609A", "lastDone": 0.042, "changePercent": 5.0, "volume": 2090000, "strikePrice": 0.042, "expiryDate": "2026-09-25", "type": "call", "premium": 59.89, "leverage": 85.2}, {"symbol": "27127", "name": "UB-GEG @EC2609B", "lastDone": 0.083, "changePercent": 6.41, "volume": 1750000, "strikePrice": 0.083, "expiryDate": "2026-09-04", "type": "call", "premium": 35.89, "leverage": 43.1}, {"symbol": "27181", "name": "SG-GEG @EC2609B", "lastDone": 0.079, "changePercent": 9.72, "volume": 1380000, "strikePrice": 0.079, "expiryDate": "2026-09-04", "type": "call", "premium": 35.77, "leverage": 45.3}, {"symbol": "24150", "name": "CT-GEG @EC2607A", "lastDone": 0.034, "changePercent": 13.33, "volume": 1360000, "strikePrice": 0.034, "expiryDate": "2026-07-09", "type": "call", "premium": 31.75, "leverage": 105.2}, {"symbol": "27013", "name": "HU-GEG @EC2612A", "lastDone": 0.123, "changePercent": 0.82, "volume": 1054000, "strikePrice": 0.123, "expiryDate": "2026-12-23", "type": "call", "premium": 37.59, "leverage": 29.1}, {"symbol": "23862", "name": "JP-GEG @EP2606A", "lastDone": 0.152, "changePercent": -8.98, "volume": 720000, "strikePrice": 0.152, "expiryDate": "2026-06-23", "type": "put", "premium": 14.06, "leverage": 23.5}, {"symbol": "24368", "name": "SG-GEG @EC2607A", "lastDone": 0.029, "changePercent": 7.41, "volume": 570000, "strikePrice": 0.029, "expiryDate": "2026-07-02", "type": "call", "premium": 31.67, "leverage": 123.4}, {"symbol": "23970", "name": "UB-GEG @EP2606A", "lastDone": 0.152, "changePercent": -9.52, "volume": 160000, "strikePrice": 0.152, "expiryDate": "2026-06-15", "type": "put", "premium": 14.11, "leverage": 23.5}, {"symbol": "29605", "name": "MB-GEG @EC2605A", "lastDone": 0.014, "changePercent": 0, "volume": 0, "strikePrice": 0.014, "expiryDate": "2026-05-05", "type": "call", "premium": 31.44, "leverage": 255.6}, {"symbol": "28809", "name": "BP-GEG @EC2604B", "lastDone": 0.013, "changePercent": 0, "volume": 0, "strikePrice": 0.013, "expiryDate": "2026-04-02", "type": "call", "premium": 59.39, "leverage": 275.2}, {"symbol": "27162", "name": "CT-GEG @EC2609A", "lastDone": 0, "changePercent": 0, "volume": 0, "strikePrice": 0, "expiryDate": "2026-09-04", "type": "call", "premium": 0, "leverage": 0}, {"symbol": "27118", "name": "CI-GEG @EC2609B", "lastDone": 0.152, "changePercent": -1.3, "volume": 0, "strikePrice": 0.152, "expiryDate": "2026-09-16", "type": "call", "premium": 26.89, "leverage": 23.5}, {"symbol": "26576", "name": "HU-GEG @EC2603A", "lastDone": 0.01, "changePercent": 0, "volume": 0, "strikePrice": 0.01, "expiryDate": "2026-03-27", "type": "call", "premium": 59.39, "leverage": 357.8}, {"symbol": "26549", "name": "JP-GEG @EC2609A", "lastDone": 0.037, "changePercent": 0, "volume": 0, "strikePrice": 0.037, "expiryDate": "2026-09-18", "type": "call", "premium": 59.78, "leverage": 96.7}, {"symbol": "26453", "name": "SG-GEG @EC2609A", "lastDone": 0.03, "changePercent": 3.45, "volume": 0, "strikePrice": 0.03, "expiryDate": "2026-09-18", "type": "call", "premium": 59.7, "leverage": 119.3}, {"symbol": "26330", "name": "UB-GEG @EC2609A", "lastDone": 0.036, "changePercent": 0, "volume": 0, "strikePrice": 0.036, "expiryDate": "2026-09-18", "type": "call", "premium": 59.86, "leverage": 99.4}, {"symbol": "26274", "name": "CI-GEG @EC2609A", "lastDone": 0.026, "changePercent": 0, "volume": 0, "strikePrice": 0.026, "expiryDate": "2026-09-18", "type": "call", "premium": 59.5, "leverage": 137.6}, {"symbol": "23804", "name": "HS-GEG @EC2606A", "lastDone": 0.013, "changePercent": -31.58, "volume": 0, "strikePrice": 0.013, "expiryDate": "2026-06-02", "type": "call", "premium": 37.34, "leverage": 275.2}, {"symbol": "23730", "name": "CI-GEG @EC2604B", "lastDone": 0.012, "changePercent": 0, "volume": 0, "strikePrice": 0.012, "expiryDate": "2026-04-27", "type": "call", "premium": 31.36, "leverage": 298.2}, {"symbol": "23720", "name": "BP-GEG @EC2606A", "lastDone": 0.015, "changePercent": 0, "volume": 0, "strikePrice": 0.015, "expiryDate": "2026-06-02", "type": "call", "premium": 37.37, "leverage": 238.5}, {"symbol": "23698", "name": "BI-GEG @EC2606A", "lastDone": 0.015, "changePercent": 0, "volume": 0, "strikePrice": 0.015, "expiryDate": "2026-06-02", "type": "call", "premium": 37.4, "leverage": 238.5}, {"symbol": "23602", "name": "UB-GEG @EC2606A", "lastDone": 0.02, "changePercent": 0, "volume": 0, "strikePrice": 0.02, "expiryDate": "2026-06-02", "type": "call", "premium": 37.53, "leverage": 178.9}, {"symbol": "23583", "name": "JP-GEG @EC2606A", "lastDone": 0.014, "changePercent": 0, "volume": 0, "strikePrice": 0.014, "expiryDate": "2026-06-02", "type": "call", "premium": 37.37, "leverage": 255.6}, {"symbol": "23518", "name": "HU-GEG @EC2606A", "lastDone": 0.01, "changePercent": 0, "volume": 0, "strikePrice": 0.01, "expiryDate": "2026-06-02", "type": "call", "premium": 37.26, "leverage": 357.8}, {"symbol": "23242", "name": "MS-GEG @EC2606A", "lastDone": 0.01, "changePercent": 0, "volume": 0, "strikePrice": 0.01, "expiryDate": "2026-06-09", "type": "call", "premium": 37.2, "leverage": 357.8}, {"symbol": "22814", "name": "CT-GEG @EC2604A", "lastDone": 0.01, "changePercent": 0, "volume": 0, "strikePrice": 0.01, "expiryDate": "2026-04-20", "type": "call", "premium": 39.97, "leverage": 357.8}, {"symbol": "22068", "name": "HS-GEG @EC2604A", "lastDone": 0.01, "changePercent": 0, "volume": 0, "strikePrice": 0.01, "expiryDate": "2026-04-20", "type": "call", "premium": 40.16, "leverage": 357.8}, {"symbol": "22019", "name": "BP-GEG @EC2604C", "lastDone": 0.015, "changePercent": 0, "volume": 0, "strikePrice": 0.015, "expiryDate": "2026-04-20", "type": "call", "premium": 40.13, "leverage": 238.5}, {"symbol": "26476", "name": "MB-GEG @EP2609A", "lastDone": 0, "changePercent": 0, "volume": 0, "strikePrice": 0, "expiryDate": "2026-09-03", "type": "put", "premium": 0, "leverage": 0}, {"symbol": "22044", "name": "BI-GEG @EP2605A", "lastDone": 0.065, "changePercent": -12.16, "volume": 0, "strikePrice": 0.065, "expiryDate": "2026-05-19", "type": "put", "premium": 19.91, "leverage": 110.1}]