[{"symbol": "26003", "name": "GJTENCT@EC2607D", "lastDone": 0.047, "changePercent": -9.62, "volume": 1332830000, "strikePrice": 0.047, "expiryDate": "2026-07-29", "type": "call", "premium": 34.88, "leverage": 108.1}, {"symbol": "25950", "name": "SGTENCT@EC2607E", "lastDone": 0.051, "changePercent": -12.07, "volume": 1150500000, "strikePrice": 0.051, "expiryDate": "2026-07-29", "type": "call", "premium": 34.96, "leverage": 99.6}, {"symbol": "26200", "name": "JPTENCT@EC2608A", "lastDone": 0.07, "changePercent": -4.11, "volume": 1051040000, "strikePrice": 0.07, "expiryDate": "2026-08-05", "type": "call", "premium": 33.36, "leverage": 72.6}, {"symbol": "25709", "name": "UBTENCT@EC2707A", "lastDone": 0.061, "changePercent": -3.17, "volume": 1014165000, "strikePrice": 0.061, "expiryDate": "2027-07-02", "type": "call", "premium": 37.99, "leverage": 16.7}, {"symbol": "25949", "name": "SGTENCT@EC2608B", "lastDone": 0.048, "changePercent": -11.11, "volume": 988220000, "strikePrice": 0.048, "expiryDate": "2026-08-03", "type": "call", "premium": 38.84, "leverage": 105.8}, {"symbol": "25954", "name": "GJTENCT@EC2607C", "lastDone": 0.041, "changePercent": 0, "volume": 535230000, "strikePrice": 0.041, "expiryDate": "2026-07-29", "type": "call", "premium": 44.01, "leverage": 123.9}, {"symbol": "26110", "name": "HSTENCT@EC2607E", "lastDone": 0.047, "changePercent": -11.32, "volume": 363570000, "strikePrice": 0.047, "expiryDate": "2026-07-29", "type": "call", "premium": 34.88, "leverage": 108.1}, {"symbol": "26301", "name": "MSTENCT@EC2608G", "lastDone": 0.091, "changePercent": -4.21, "volume": 323230000, "strikePrice": 0.091, "expiryDate": "2026-08-24", "type": "call", "premium": 29.62, "leverage": 55.8}, {"symbol": "27221", "name": "BITENCT@EC2609C", "lastDone": 0.111, "changePercent": -6.72, "volume": 297550000, "strikePrice": 0.111, "expiryDate": "2026-09-25", "type": "call", "premium": 32.97, "leverage": 45.8}, {"symbol": "26310", "name": "GJTENCT@EP2608A", "lastDone": 0.224, "changePercent": 0.9, "volume": 224420000, "strikePrice": 0.224, "expiryDate": "2026-08-03", "type": "call", "premium": 12.59, "leverage": 22.7}, {"symbol": "25613", "name": "DSTENCT@EC2609B", "lastDone": 0.045, "changePercent": -6.25, "volume": 211640000, "strikePrice": 0.045, "expiryDate": "2026-09-23", "type": "call", "premium": 54.31, "leverage": 112.9}, {"symbol": "16185", "name": "DSTENCT@EC2606A", "lastDone": 0.051, "changePercent": -5.56, "volume": 210200000, "strikePrice": 0.051, "expiryDate": "2026-06-23", "type": "call", "premium": 9.45, "leverage": 19.9}, {"symbol": "26167", "name": "UBTENCT@EC2608C", "lastDone": 0.068, "changePercent": -5.56, "volume": 153640000, "strikePrice": 0.068, "expiryDate": "2026-08-05", "type": "call", "premium": 33.32, "leverage": 74.7}, {"symbol": "27089", "name": "BPTENCT@EP2611B", "lastDone": 0.137, "changePercent": -5.52, "volume": 132080000, "strikePrice": 0.137, "expiryDate": "2026-11-23", "type": "call", "premium": 24.0, "leverage": 37.1}, {"symbol": "16004", "name": "BPTENCT@EC2606A", "lastDone": 0.046, "changePercent": -4.17, "volume": 127800000, "strikePrice": 0.046, "expiryDate": "2026-06-23", "type": "call", "premium": 8.96, "leverage": 22.1}, {"symbol": "26151", "name": "CTTENCT@EC2608C", "lastDone": 0.107, "changePercent": -3.6, "volume": 114520000, "strikePrice": 0.107, "expiryDate": "2026-08-19", "type": "call", "premium": 25.9, "leverage": 47.5}, {"symbol": "26075", "name": "BITENCT@EP2608A", "lastDone": 0.204, "changePercent": 2.0, "volume": 89650000, "strikePrice": 0.204, "expiryDate": "2026-08-03", "type": "call", "premium": 12.19, "leverage": 24.9}, {"symbol": "25685", "name": "UBTENCT@EC2611A", "lastDone": 0.074, "changePercent": -3.9, "volume": 83640000, "strikePrice": 0.074, "expiryDate": "2026-11-25", "type": "call", "premium": 56.85, "leverage": 68.6}, {"symbol": "25651", "name": "MSTENCT@EC2608B", "lastDone": 0.049, "changePercent": -3.92, "volume": 79840000, "strikePrice": 0.049, "expiryDate": "2026-08-05", "type": "call", "premium": 38.76, "leverage": 103.7}, {"symbol": "25893", "name": "MSTENCT@EC2607B", "lastDone": 0.027, "changePercent": 0, "volume": 75840000, "strikePrice": 0.027, "expiryDate": "2026-07-29", "type": "call", "premium": 53.73, "leverage": 188.1}, {"symbol": "25920", "name": "BPTENCT@EC2609C", "lastDone": 0.089, "changePercent": -5.32, "volume": 60770000, "strikePrice": 0.089, "expiryDate": "2026-09-02", "type": "call", "premium": 31.67, "leverage": 57.1}, {"symbol": "25990", "name": "MSTENCT@EC2607C", "lastDone": 0.053, "changePercent": -3.64, "volume": 60670000, "strikePrice": 0.053, "expiryDate": "2026-07-29", "type": "call", "premium": 35.0, "leverage": 95.8}, {"symbol": "58281", "name": "SG#TENCTRC2610C", "lastDone": 0.041, "changePercent": -10.87, "volume": 59545000, "strikePrice": 0.041, "expiryDate": "2026-10-28", "type": "call", "premium": 0.89, "leverage": 24.8}, {"symbol": "27002", "name": "BPTENCT@EP2611A", "lastDone": 0.129, "changePercent": -2.27, "volume": 58650000, "strikePrice": 0.129, "expiryDate": "2026-11-03", "type": "call", "premium": 22.05, "leverage": 39.4}, {"symbol": "26227", "name": "MSTENCT@EC2608F", "lastDone": 0.101, "changePercent": -4.72, "volume": 58030000, "strikePrice": 0.101, "expiryDate": "2026-08-12", "type": "call", "premium": 25.88, "leverage": 50.3}, {"symbol": "26252", "name": "BPTENCT@EC2608C", "lastDone": 0.092, "changePercent": -5.15, "volume": 57930000, "strikePrice": 0.092, "expiryDate": "2026-08-24", "type": "call", "premium": 29.64, "leverage": 55.2}, {"symbol": "25097", "name": "JPTENCT@EC2609A", "lastDone": 0.037, "changePercent": -7.5, "volume": 54150000, "strikePrice": 0.037, "expiryDate": "2026-09-11", "type": "call", "premium": 21.85, "leverage": 27.5}, {"symbol": "63345", "name": "SG#TENCTRC2609I", "lastDone": 0.072, "changePercent": -6.49, "volume": 53780000, "strikePrice": 0.072, "expiryDate": "2026-09-29", "type": "call", "premium": 0.98, "leverage": 14.1}, {"symbol": "26129", "name": "MSTENCT@EC2608E", "lastDone": 0.041, "changePercent": -4.65, "volume": 47580000, "strikePrice": 0.041, "expiryDate": "2026-08-03", "type": "call", "premium": 43.2, "leverage": 123.9}, {"symbol": "26063", "name": "SGTENCT@EP2608A", "lastDone": 0.205, "changePercent": 2.5, "volume": 45660000, "strikePrice": 0.205, "expiryDate": "2026-08-03", "type": "call", "premium": 12.21, "leverage": 24.8}, {"symbol": "21665", "name": "MSTENCT@EC2703A", "lastDone": 0.039, "changePercent": -2.5, "volume": 40660000, "strikePrice": 0.039, "expiryDate": "2027-03-17", "type": "call", "premium": 39.54, "leverage": 26.1}, {"symbol": "15505", "name": "UBTENCT@EC2608A", "lastDone": 0.028, "changePercent": -3.45, "volume": 40100000, "strikePrice": 0.028, "expiryDate": "2026-08-26", "type": "call", "premium": 22.83, "leverage": 36.3}, {"symbol": "21974", "name": "BPTENCT@EP2606A", "lastDone": 0.265, "changePercent": 3.92, "volume": 39950000, "strikePrice": 0.265, "expiryDate": "2026-06-23", "type": "call", "premium": 6.79, "leverage": 19.2}, {"symbol": "26259", "name": "UBTENCT@EC2608E", "lastDone": 0.107, "changePercent": -7.76, "volume": 37140000, "strikePrice": 0.107, "expiryDate": "2026-08-12", "type": "call", "premium": 26.0, "leverage": 47.5}, {"symbol": "26038", "name": "MSTENCT@EC2608D", "lastDone": 0.069, "changePercent": -4.17, "volume": 36510000, "strikePrice": 0.069, "expiryDate": "2026-08-12", "type": "call", "premium": 33.25, "leverage": 73.6}, {"symbol": "15213", "name": "CITENCT@EC2607A", "lastDone": 0.019, "changePercent": -36.67, "volume": 35000000, "strikePrice": 0.019, "expiryDate": "2026-07-24", "type": "call", "premium": 24.31, "leverage": 53.5}, {"symbol": "69620", "name": "HS#TENCTRC26083", "lastDone": 0.074, "changePercent": -6.33, "volume": 34385000, "strikePrice": 0.074, "expiryDate": "2026-08-24", "type": "call", "premium": 1.14, "leverage": 13.7}, {"symbol": "56402", "name": "SG#TENCTRC2609N", "lastDone": 0.029, "changePercent": -19.44, "volume": 33725000, "strikePrice": 0.029, "expiryDate": "2026-09-28", "type": "call", "premium": 0.69, "leverage": 35.0}, {"symbol": "25602", "name": "MSTENCT@EC2610A", "lastDone": 0.029, "changePercent": -6.45, "volume": 32450000, "strikePrice": 0.029, "expiryDate": "2026-10-27", "type": "call", "premium": 73.68, "leverage": 175.2}, {"symbol": "26502", "name": "CTTENCT@EP2609A", "lastDone": 0.13, "changePercent": 1.56, "volume": 32230000, "strikePrice": 0.13, "expiryDate": "2026-09-03", "type": "call", "premium": 18.13, "leverage": 39.1}, {"symbol": "27058", "name": "SGTENCT@EP2609A", "lastDone": 0.202, "changePercent": 0, "volume": 31340000, "strikePrice": 0.202, "expiryDate": "2026-09-23", "type": "call", "premium": 15.43, "leverage": 25.1}, {"symbol": "26484", "name": "MSTENCT@EP2608B", "lastDone": 0.196, "changePercent": 1.03, "volume": 30940000, "strikePrice": 0.196, "expiryDate": "2026-08-03", "type": "call", "premium": 12.04, "leverage": 25.9}, {"symbol": "57745", "name": "UB#TENCTRP2812R", "lastDone": 0.107, "changePercent": 1.9, "volume": 30510000, "strikePrice": 0.107, "expiryDate": "2028-12-07", "type": "call", "premium": -2.3, "leverage": 9.5}, {"symbol": "25649", "name": "MSTENCT@EC2609B", "lastDone": 0.048, "changePercent": -4.0, "volume": 30310000, "strikePrice": 0.048, "expiryDate": "2026-09-23", "type": "call", "premium": 54.37, "leverage": 105.8}, {"symbol": "25902", "name": "CTTENCT@EC2607B", "lastDone": 0.051, "changePercent": -10.53, "volume": 29550000, "strikePrice": 0.051, "expiryDate": "2026-07-29", "type": "call", "premium": 34.86, "leverage": 99.6}, {"symbol": "14683", "name": "HSTENCT@EC2609A", "lastDone": 0.03, "changePercent": -9.09, "volume": 26640000, "strikePrice": 0.03, "expiryDate": "2026-09-11", "type": "call", "premium": 21.16, "leverage": 33.9}, {"symbol": "26231", "name": "BPTENCT@EC2608A", "lastDone": 0.063, "changePercent": -7.35, "volume": 25510000, "strikePrice": 0.063, "expiryDate": "2026-08-05", "type": "call", "premium": 33.13, "leverage": 80.6}, {"symbol": "25896", "name": "JPTENCT@EC2607D", "lastDone": 0.04, "changePercent": -4.76, "volume": 25510000, "strikePrice": 0.04, "expiryDate": "2026-07-29", "type": "call", "premium": 43.99, "leverage": 127.0}, {"symbol": "60999", "name": "SG#TENCTRP2812O", "lastDone": 0.101, "changePercent": 8.6, "volume": 24845000, "strikePrice": 0.101, "expiryDate": "2028-12-29", "type": "call", "premium": -1.87, "leverage": 10.1}, {"symbol": "26475", "name": "MBTENCT@EP2609A", "lastDone": 0.182, "changePercent": 0, "volume": 24830000, "strikePrice": 0.182, "expiryDate": "2026-09-30", "type": "call", "premium": 17.19, "leverage": 27.9}, {"symbol": "63210", "name": "HS#TENCTRC2608U", "lastDone": 0.064, "changePercent": -7.25, "volume": 24530000, "strikePrice": 0.064, "expiryDate": "2026-08-06", "type": "call", "premium": 1.14, "leverage": 15.9}, {"symbol": "27151", "name": "MSTENCT@EP2610A", "lastDone": 0.128, "changePercent": -1.54, "volume": 24420000, "strikePrice": 0.128, "expiryDate": "2026-10-27", "type": "call", "premium": 22.07, "leverage": 39.7}, {"symbol": "58284", "name": "SG#TENCTRC2610D", "lastDone": 0.062, "changePercent": -8.82, "volume": 24405000, "strikePrice": 0.062, "expiryDate": "2026-10-30", "type": "call", "premium": 0.98, "leverage": 16.4}, {"symbol": "26870", "name": "MSTENCT@EP2608C", "lastDone": 0.125, "changePercent": 0.81, "volume": 24260000, "strikePrice": 0.125, "expiryDate": "2026-08-27", "type": "call", "premium": 18.07, "leverage": 40.6}, {"symbol": "62650", "name": "BI#TENCTRC2612K", "lastDone": 0.061, "changePercent": -7.58, "volume": 23715000, "strikePrice": 0.061, "expiryDate": "2026-12-31", "type": "call", "premium": 1.71, "leverage": 16.7}, {"symbol": "20601", "name": "MSTENCT@EC2707A", "lastDone": 0.056, "changePercent": -5.08, "volume": 23620000, "strikePrice": 0.056, "expiryDate": "2027-07-09", "type": "call", "premium": 37.4, "leverage": 18.1}, {"symbol": "14707", "name": "MSTENCT@EP2612A", "lastDone": 0.076, "changePercent": 2.7, "volume": 22850000, "strikePrice": 0.076, "expiryDate": "2026-12-17", "type": "call", "premium": 12.68, "leverage": 13.4}, {"symbol": "59719", "name": "JP#TENCTRC26061", "lastDone": 0.052, "changePercent": -8.77, "volume": 22745000, "strikePrice": 0.052, "expiryDate": "2026-06-12", "type": "call", "premium": 0.79, "leverage": 19.5}, {"symbol": "63202", "name": "HS#TENCTRC2609O", "lastDone": 0.085, "changePercent": -5.56, "volume": 22615000, "strikePrice": 0.085, "expiryDate": "2026-09-07", "type": "call", "premium": 1.24, "leverage": 12.0}, {"symbol": "25653", "name": "MSTENCT@EC2610B", "lastDone": 0.056, "changePercent": -3.45, "volume": 22530000, "strikePrice": 0.056, "expiryDate": "2026-10-09", "type": "call", "premium": 52.68, "leverage": 90.7}, {"symbol": "16022", "name": "SGTENCT@EC2606A", "lastDone": 0.045, "changePercent": -6.25, "volume": 22400000, "strikePrice": 0.045, "expiryDate": "2026-06-23", "type": "call", "premium": 8.86, "leverage": 22.6}, {"symbol": "14652", "name": "SGTENCT@EC2609A", "lastDone": 0.033, "changePercent": -5.71, "volume": 21885000, "strikePrice": 0.033, "expiryDate": "2026-09-11", "type": "call", "premium": 21.46, "leverage": 30.8}, {"symbol": "25906", "name": "MBTENCT@EC2608A", "lastDone": 0.061, "changePercent": -25.61, "volume": 20900000, "strikePrice": 0.061, "expiryDate": "2026-08-10", "type": "call", "premium": 43.5, "leverage": 83.3}, {"symbol": "15458", "name": "MSTENCT@EC2608A", "lastDone": 0.025, "changePercent": -7.41, "volume": 20750000, "strikePrice": 0.025, "expiryDate": "2026-08-26", "type": "call", "premium": 22.54, "leverage": 40.6}, {"symbol": "59002", "name": "JP#TENCTRC2608V", "lastDone": 0.07, "changePercent": -4.11, "volume": 20690000, "strikePrice": 0.07, "expiryDate": "2026-08-14", "type": "call", "premium": 0.75, "leverage": 14.5}, {"symbol": "19459", "name": "BPTENCT@EP2605A", "lastDone": 0.05, "changePercent": 2.04, "volume": 19450000, "strikePrice": 0.05, "expiryDate": "2026-05-05", "type": "call", "premium": 10.43, "leverage": 101.6}, {"symbol": "19521", "name": "MSTENCT@EC2806A", "lastDone": 0.065, "changePercent": -4.41, "volume": 19000000, "strikePrice": 0.065, "expiryDate": "2028-06-29", "type": "call", "premium": 59.94, "leverage": 15.6}, {"symbol": "53087", "name": "UB#TENCTRC2608W", "lastDone": 0.027, "changePercent": -12.9, "volume": 18600000, "strikePrice": 0.027, "expiryDate": "2026-08-12", "type": "call", "premium": 0.65, "leverage": 37.6}, {"symbol": "14438", "name": "DSTENCT@EC2609A", "lastDone": 0.036, "changePercent": -5.26, "volume": 18600000, "strikePrice": 0.036, "expiryDate": "2026-09-18", "type": "call", "premium": 21.65, "leverage": 28.2}, {"symbol": "58805", "name": "UB#TENCTRC2607V", "lastDone": 0.081, "changePercent": -5.81, "volume": 18350000, "strikePrice": 0.081, "expiryDate": "2026-07-13", "type": "call", "premium": 0.85, "leverage": 12.5}, {"symbol": "58894", "name": "SG#TENCTRC2609G", "lastDone": 0.053, "changePercent": -7.02, "volume": 18105000, "strikePrice": 0.053, "expiryDate": "2026-09-28", "type": "call", "premium": 1.08, "leverage": 19.2}, {"symbol": "14210", "name": "CTTENCT@EP2612A", "lastDone": 0.071, "changePercent": 1.43, "volume": 17750000, "strikePrice": 0.071, "expiryDate": "2026-12-17", "type": "call", "premium": 12.18, "leverage": 14.3}, {"symbol": "14186", "name": "HSTENCT@EP2612A", "lastDone": 0.077, "changePercent": 1.32, "volume": 17750000, "strikePrice": 0.077, "expiryDate": "2026-12-24", "type": "call", "premium": 12.73, "leverage": 13.2}, {"symbol": "69328", "name": "BP#TENCTRC2608B", "lastDone": 0.034, "changePercent": -8.11, "volume": 17445000, "strikePrice": 0.034, "expiryDate": "2026-08-31", "type": "call", "premium": 0.83, "leverage": 29.9}, {"symbol": "58800", "name": "UB#TENCTRC2607T", "lastDone": 0.061, "changePercent": -7.58, "volume": 17350000, "strikePrice": 0.061, "expiryDate": "2026-07-22", "type": "call", "premium": 0.85, "leverage": 16.7}, {"symbol": "26010", "name": "UBTENCT@EC2607D", "lastDone": 0.056, "changePercent": -5.08, "volume": 17330000, "strikePrice": 0.056, "expiryDate": "2026-07-29", "type": "call", "premium": 35.06, "leverage": 90.7}, {"symbol": "27112", "name": "HUTENCT@EC2609D", "lastDone": 0.11, "changePercent": -3.51, "volume": 16930000, "strikePrice": 0.11, "expiryDate": "2026-09-25", "type": "call", "premium": 32.95, "leverage": 46.2}, {"symbol": "15921", "name": "MSTENCT@EC2606C", "lastDone": 0.043, "changePercent": -6.52, "volume": 16600000, "strikePrice": 0.043, "expiryDate": "2026-06-23", "type": "call", "premium": 8.66, "leverage": 23.6}, {"symbol": "54436", "name": "BP#TENCTRC2608C", "lastDone": 0.132, "changePercent": -2.22, "volume": 16360000, "strikePrice": 0.132, "expiryDate": "2026-08-31", "type": "call", "premium": 0.83, "leverage": 7.7}, {"symbol": "26258", "name": "UBTENCT@EC2608D", "lastDone": 0.097, "changePercent": -4.9, "volume": 16020000, "strikePrice": 0.097, "expiryDate": "2026-08-24", "type": "call", "premium": 29.74, "leverage": 52.4}, {"symbol": "26244", "name": "BPTENCT@EP2608A", "lastDone": 0.193, "changePercent": 1.58, "volume": 15180000, "strikePrice": 0.193, "expiryDate": "2026-08-04", "type": "call", "premium": 11.98, "leverage": 26.3}, {"symbol": "14826", "name": "JPTENCT@EC2607A", "lastDone": 0.021, "changePercent": -8.7, "volume": 14450000, "strikePrice": 0.021, "expiryDate": "2026-07-31", "type": "call", "premium": 24.55, "leverage": 48.4}, {"symbol": "63477", "name": "BP#TENCTRC2606Y", "lastDone": 0.049, "changePercent": -9.26, "volume": 14050000, "strikePrice": 0.049, "expiryDate": "2026-06-30", "type": "call", "premium": 0.73, "leverage": 20.7}, {"symbol": "58296", "name": "SG#TENCTRC2611B", "lastDone": 0.085, "changePercent": -3.41, "volume": 13530000, "strikePrice": 0.085, "expiryDate": "2026-11-25", "type": "call", "premium": 1.28, "leverage": 12.0}, {"symbol": "62983", "name": "JP#TENCTRC2609R", "lastDone": 0.082, "changePercent": -5.75, "volume": 13395000, "strikePrice": 0.082, "expiryDate": "2026-09-11", "type": "call", "premium": 0.94, "leverage": 12.4}, {"symbol": "25541", "name": "CITENCT@EC2609A", "lastDone": 0.035, "changePercent": -7.89, "volume": 13020000, "strikePrice": 0.035, "expiryDate": "2026-09-11", "type": "call", "premium": 21.46, "leverage": 29.0}, {"symbol": "16480", "name": "BPTENCT@EC2703A", "lastDone": 0.04, "changePercent": -4.76, "volume": 12905000, "strikePrice": 0.04, "expiryDate": "2027-03-17", "type": "call", "premium": 39.57, "leverage": 25.4}, {"symbol": "23539", "name": "SGTENCT@EC2608A", "lastDone": 0.027, "changePercent": -3.57, "volume": 12800000, "strikePrice": 0.027, "expiryDate": "2026-08-26", "type": "call", "premium": 22.74, "leverage": 37.6}, {"symbol": "25948", "name": "SGTENCT@EC2607D", "lastDone": 0.037, "changePercent": -7.5, "volume": 12730000, "strikePrice": 0.037, "expiryDate": "2026-07-29", "type": "call", "premium": 43.94, "leverage": 137.3}, {"symbol": "62930", "name": "MS#TENCTRC2611B", "lastDone": 0.073, "changePercent": -6.41, "volume": 12595000, "strikePrice": 0.073, "expiryDate": "2026-11-30", "type": "call", "premium": 1.52, "leverage": 13.9}, {"symbol": "58299", "name": "SG#TENCTRC2611C", "lastDone": 0.106, "changePercent": -5.36, "volume": 12475000, "strikePrice": 0.106, "expiryDate": "2026-11-26", "type": "call", "premium": 1.38, "leverage": 9.6}, {"symbol": "26379", "name": "HUTENCT@EC2608B", "lastDone": 0.108, "changePercent": -5.26, "volume": 12170000, "strikePrice": 0.108, "expiryDate": "2026-08-12", "type": "call", "premium": 26.02, "leverage": 47.0}, {"symbol": "25942", "name": "UBTENCT@EC2607C", "lastDone": 0.051, "changePercent": -3.77, "volume": 12110000, "strikePrice": 0.051, "expiryDate": "2026-07-29", "type": "call", "premium": 38.9, "leverage": 99.6}, {"symbol": "59945", "name": "UB#TENCTRC2608F", "lastDone": 0.04, "changePercent": -9.09, "volume": 11850000, "strikePrice": 0.04, "expiryDate": "2026-08-03", "type": "call", "premium": 0.94, "leverage": 25.4}, {"symbol": "14148", "name": "HSTENCT@EC2607A", "lastDone": 0.071, "changePercent": -5.33, "volume": 11780000, "strikePrice": 0.071, "expiryDate": "2026-07-02", "type": "call", "premium": 5.41, "leverage": 14.3}, {"symbol": "60020", "name": "HS#TENCTRP2811D", "lastDone": 0.095, "changePercent": 3.26, "volume": 11755000, "strikePrice": 0.095, "expiryDate": "2028-11-06", "type": "call", "premium": -1.52, "leverage": 10.7}, {"symbol": "23967", "name": "MSTENCT@EP2606A", "lastDone": 0.27, "changePercent": 0, "volume": 11590000, "strikePrice": 0.27, "expiryDate": "2026-06-23", "type": "call", "premium": 6.93, "leverage": 18.8}, {"symbol": "63207", "name": "HS#TENCTRC2612B", "lastDone": 0.153, "changePercent": -3.16, "volume": 10525000, "strikePrice": 0.153, "expiryDate": "2026-12-21", "type": "call", "premium": 1.04, "leverage": 6.6}, {"symbol": "15614", "name": "CTTENCT@EC2608A", "lastDone": 0.025, "changePercent": -7.41, "volume": 10200000, "strikePrice": 0.025, "expiryDate": "2026-08-26", "type": "call", "premium": 22.54, "leverage": 40.6}, {"symbol": "58047", "name": "UB#TENCTRP2812L", "lastDone": 0.123, "changePercent": 1.65, "volume": 10065000, "strikePrice": 0.123, "expiryDate": "2028-12-27", "type": "call", "premium": -2.7, "leverage": 8.3}]