[{"symbol": "25136", "name": "GJPOMRT@EC2606A", "lastDone": 0.052, "changePercent": -14.75, "volume": 376722000, "strikePrice": 0.052, "expiryDate": "2026-06-03", "type": "call", "premium": 33.78, "leverage": 40.3}, {"symbol": "24140", "name": "GJPOMRT@EP2605B", "lastDone": 0.064, "changePercent": 6.67, "volume": 226040000, "strikePrice": 0.064, "expiryDate": "2026-05-22", "type": "call", "premium": 18.18, "leverage": 32.8}, {"symbol": "23066", "name": "SGPOMRT@EP2606A", "lastDone": 0.08, "changePercent": 8.11, "volume": 127560000, "strikePrice": 0.08, "expiryDate": "2026-06-01", "type": "call", "premium": 18.89, "leverage": 26.2}, {"symbol": "24839", "name": "BIPOMRT@EC2606A", "lastDone": 0.114, "changePercent": -14.29, "volume": 91100000, "strikePrice": 0.114, "expiryDate": "2026-06-30", "type": "call", "premium": 26.66, "leverage": 18.4}, {"symbol": "26621", "name": "GJPOMRT@EC2606C", "lastDone": 0.109, "changePercent": -9.92, "volume": 86900000, "strikePrice": 0.109, "expiryDate": "2026-06-23", "type": "call", "premium": 26.43, "leverage": 19.2}, {"symbol": "23043", "name": "GJPOMRT@EP2605A", "lastDone": 0.105, "changePercent": 8.25, "volume": 81280000, "strikePrice": 0.105, "expiryDate": "2026-05-21", "type": "call", "premium": 14.94, "leverage": 20.0}, {"symbol": "15457", "name": "BIPOMRT@EP2609A", "lastDone": 0.181, "changePercent": 1.12, "volume": 71334000, "strikePrice": 0.181, "expiryDate": "2026-09-23", "type": "call", "premium": 22.81, "leverage": 11.6}, {"symbol": "58650", "name": "HS#POMRTRP2811A", "lastDone": 0.041, "changePercent": 13.89, "volume": 62470000, "strikePrice": 0.041, "expiryDate": "2028-11-20", "type": "call", "premium": -0.43, "leverage": 10.2}, {"symbol": "22788", "name": "HSPOMRT@EC2605B", "lastDone": 0.1, "changePercent": -13.79, "volume": 59340000, "strikePrice": 0.1, "expiryDate": "2026-05-26", "type": "call", "premium": 19.24, "leverage": 21.0}, {"symbol": "23451", "name": "CTPOMRT@EC2605A", "lastDone": 0.095, "changePercent": -12.84, "volume": 54900000, "strikePrice": 0.095, "expiryDate": "2026-05-18", "type": "call", "premium": 18.9, "leverage": 22.1}, {"symbol": "22126", "name": "MBPOMRT@EP2608A", "lastDone": 0.134, "changePercent": 9.84, "volume": 34480000, "strikePrice": 0.134, "expiryDate": "2026-08-04", "type": "call", "premium": 25.29, "leverage": 15.6}, {"symbol": "25974", "name": "MBPOMRT@EC2608A", "lastDone": 0.062, "changePercent": -12.68, "volume": 27680000, "strikePrice": 0.062, "expiryDate": "2026-08-17", "type": "call", "premium": 74.71, "leverage": 33.8}, {"symbol": "56389", "name": "SG#POMRTRC2610A", "lastDone": 0.053, "changePercent": -11.67, "volume": 23290000, "strikePrice": 0.053, "expiryDate": "2026-10-29", "type": "call", "premium": 0.81, "leverage": 7.9}, {"symbol": "57271", "name": "HS#POMRTRC2609E", "lastDone": 0.072, "changePercent": -10.0, "volume": 21530000, "strikePrice": 0.072, "expiryDate": "2026-09-17", "type": "call", "premium": 0.67, "leverage": 5.8}, {"symbol": "23585", "name": "JPPOMRT@EC2606A", "lastDone": 0.057, "changePercent": -12.31, "volume": 20890000, "strikePrice": 0.057, "expiryDate": "2026-06-03", "type": "call", "premium": 34.02, "leverage": 36.8}, {"symbol": "60044", "name": "HS#POMRTRC2608G", "lastDone": 0.085, "changePercent": -7.61, "volume": 20590000, "strikePrice": 0.085, "expiryDate": "2026-08-27", "type": "call", "premium": 0.91, "leverage": 4.9}, {"symbol": "21787", "name": "HSPOMRT@EP2606A", "lastDone": 0.16, "changePercent": 5.96, "volume": 19892000, "strikePrice": 0.16, "expiryDate": "2026-06-30", "type": "call", "premium": 17.02, "leverage": 13.1}, {"symbol": "59495", "name": "SG#POMRTRC2609C", "lastDone": 0.072, "changePercent": -10.0, "volume": 18750000, "strikePrice": 0.072, "expiryDate": "2026-09-28", "type": "call", "premium": 0.57, "leverage": 5.8}, {"symbol": "25398", "name": "UBPOMRT@EP2607C", "lastDone": 0.147, "changePercent": 5.0, "volume": 17800000, "strikePrice": 0.147, "expiryDate": "2026-07-28", "type": "call", "premium": 19.81, "leverage": 14.3}, {"symbol": "68843", "name": "HS#POMRTRP2812C", "lastDone": 0.067, "changePercent": 9.84, "volume": 17190000, "strikePrice": 0.067, "expiryDate": "2028-12-04", "type": "call", "premium": -1.38, "leverage": 6.3}, {"symbol": "61511", "name": "HS#POMRTRC2608H", "lastDone": 0.057, "changePercent": -9.52, "volume": 15780000, "strikePrice": 0.057, "expiryDate": "2026-08-31", "type": "call", "premium": 0.43, "leverage": 7.4}, {"symbol": "26952", "name": "MSPOMRT@EP2609A", "lastDone": 0.18, "changePercent": 4.65, "volume": 15608000, "strikePrice": 0.18, "expiryDate": "2026-09-11", "type": "call", "premium": 22.71, "leverage": 11.6}, {"symbol": "17729", "name": "MBPOMRT@EC2703A", "lastDone": 0.055, "changePercent": -3.51, "volume": 14400000, "strikePrice": 0.055, "expiryDate": "2027-03-22", "type": "call", "premium": 56.25, "leverage": 7.6}, {"symbol": "24946", "name": "SGPOMRT@EP2607A", "lastDone": 0.09, "changePercent": 7.14, "volume": 14372000, "strikePrice": 0.09, "expiryDate": "2026-07-28", "type": "call", "premium": 26.61, "leverage": 23.3}, {"symbol": "62833", "name": "SG#POMRTRC2608F", "lastDone": 0.093, "changePercent": -7.0, "volume": 14100000, "strikePrice": 0.093, "expiryDate": "2026-08-27", "type": "call", "premium": 0.33, "leverage": 4.5}, {"symbol": "25399", "name": "UBPOMRT@EP2609A", "lastDone": 0.183, "changePercent": 3.98, "volume": 13924000, "strikePrice": 0.183, "expiryDate": "2026-09-23", "type": "call", "premium": 22.9, "leverage": 11.5}, {"symbol": "17259", "name": "BIPOMRT@EC2612A", "lastDone": 0.079, "changePercent": -4.82, "volume": 13920000, "strikePrice": 0.079, "expiryDate": "2026-12-23", "type": "call", "premium": 23.9, "leverage": 5.3}, {"symbol": "26221", "name": "HSPOMRT@EC2608B", "lastDone": 0.071, "changePercent": -5.33, "volume": 13120000, "strikePrice": 0.071, "expiryDate": "2026-08-24", "type": "call", "premium": 65.56, "leverage": 29.5}, {"symbol": "22811", "name": "MSPOMRT@EC2604B", "lastDone": 0.032, "changePercent": -21.95, "volume": 13118000, "strikePrice": 0.032, "expiryDate": "2026-04-24", "type": "call", "premium": 25.63, "leverage": 65.5}, {"symbol": "67252", "name": "SG#POMRTRP2812R", "lastDone": 0.069, "changePercent": 6.15, "volume": 13030000, "strikePrice": 0.069, "expiryDate": "2028-12-27", "type": "call", "premium": -1.38, "leverage": 6.1}, {"symbol": "23351", "name": "MSPOMRT@EC2606A", "lastDone": 0.098, "changePercent": -9.26, "volume": 12962000, "strikePrice": 0.098, "expiryDate": "2026-06-10", "type": "call", "premium": 23.95, "leverage": 21.4}, {"symbol": "23400", "name": "CTPOMRT@EC2606A", "lastDone": 0.061, "changePercent": -12.86, "volume": 12632000, "strikePrice": 0.061, "expiryDate": "2026-06-10", "type": "call", "premium": 34.11, "leverage": 34.4}, {"symbol": "22064", "name": "HSPOMRT@EC2605A", "lastDone": 0.041, "changePercent": -18.0, "volume": 12250000, "strikePrice": 0.041, "expiryDate": "2026-05-04", "type": "call", "premium": 25.96, "leverage": 51.1}, {"symbol": "25400", "name": "UBPOMRT@EP2606A", "lastDone": 0.159, "changePercent": 6.0, "volume": 12208000, "strikePrice": 0.159, "expiryDate": "2026-06-25", "type": "call", "premium": 17.46, "leverage": 13.2}, {"symbol": "25120", "name": "UBPOMRT@EP2612A", "lastDone": 0.197, "changePercent": 2.6, "volume": 11500000, "strikePrice": 0.197, "expiryDate": "2026-12-22", "type": "call", "premium": 30.25, "leverage": 10.6}, {"symbol": "23397", "name": "MBPOMRT@EC2606A", "lastDone": 0.12, "changePercent": -9.77, "volume": 10820000, "strikePrice": 0.12, "expiryDate": "2026-06-30", "type": "call", "premium": 26.85, "leverage": 17.5}, {"symbol": "26768", "name": "SGPOMRT@EC2607A", "lastDone": 0.122, "changePercent": -8.96, "volume": 10740000, "strikePrice": 0.122, "expiryDate": "2026-07-24", "type": "call", "premium": 32.77, "leverage": 17.2}, {"symbol": "23171", "name": "CTPOMRT@EP2605A", "lastDone": 0.067, "changePercent": 9.84, "volume": 10600000, "strikePrice": 0.067, "expiryDate": "2026-05-22", "type": "call", "premium": 18.32, "leverage": 31.3}, {"symbol": "25143", "name": "CTPOMRT@EP2607A", "lastDone": 0.143, "changePercent": 5.93, "volume": 10090000, "strikePrice": 0.143, "expiryDate": "2026-07-27", "type": "call", "premium": 30.26, "leverage": 29.3}, {"symbol": "23059", "name": "UBPOMRT@EP2607B", "lastDone": 0.11, "changePercent": 4.76, "volume": 10020000, "strikePrice": 0.11, "expiryDate": "2026-07-28", "type": "call", "premium": 24.19, "leverage": 19.1}, {"symbol": "26831", "name": "MSPOMRT@EC2607A", "lastDone": 0.123, "changePercent": -6.82, "volume": 9560000, "strikePrice": 0.123, "expiryDate": "2026-07-24", "type": "call", "premium": 32.81, "leverage": 17.0}, {"symbol": "24910", "name": "UBPOMRT@EC2606C", "lastDone": 0.108, "changePercent": -8.47, "volume": 9460000, "strikePrice": 0.108, "expiryDate": "2026-06-23", "type": "call", "premium": 26.38, "leverage": 19.4}, {"symbol": "57407", "name": "UB#POMRTRC2609D", "lastDone": 0.076, "changePercent": -8.43, "volume": 9170000, "strikePrice": 0.076, "expiryDate": "2026-09-11", "type": "call", "premium": 0.67, "leverage": 5.5}, {"symbol": "68934", "name": "SG#POMRTRP2812U", "lastDone": 0.052, "changePercent": 13.04, "volume": 9140000, "strikePrice": 0.052, "expiryDate": "2028-12-29", "type": "call", "premium": -0.67, "leverage": 8.1}, {"symbol": "60283", "name": "UB#POMRTRC2608B", "lastDone": 0.191, "changePercent": -11.16, "volume": 8740000, "strikePrice": 0.191, "expiryDate": "2026-08-27", "type": "call", "premium": 1.19, "leverage": 11.0}, {"symbol": "21815", "name": "DSPOMRT@EC2609A", "lastDone": 0.047, "changePercent": -6.0, "volume": 8120000, "strikePrice": 0.047, "expiryDate": "2026-09-23", "type": "call", "premium": 30.58, "leverage": 8.9}, {"symbol": "24863", "name": "UBPOMRT@EC2607A", "lastDone": 0.13, "changePercent": -9.72, "volume": 8060000, "strikePrice": 0.13, "expiryDate": "2026-07-24", "type": "call", "premium": 33.15, "leverage": 16.1}, {"symbol": "21649", "name": "CTPOMRT@EP2609A", "lastDone": 0.187, "changePercent": 5.06, "volume": 8016000, "strikePrice": 0.187, "expiryDate": "2026-09-23", "type": "call", "premium": 23.09, "leverage": 11.2}, {"symbol": "23598", "name": "UBPOMRT@EC2606A", "lastDone": 0.057, "changePercent": -13.64, "volume": 7946000, "strikePrice": 0.057, "expiryDate": "2026-06-03", "type": "call", "premium": 34.02, "leverage": 36.8}, {"symbol": "20635", "name": "HSPOMRT@EC2706A", "lastDone": 0.076, "changePercent": -3.8, "volume": 7430000, "strikePrice": 0.076, "expiryDate": "2027-06-30", "type": "call", "premium": 46.91, "leverage": 5.5}, {"symbol": "65175", "name": "UB#POMRTRP2812I", "lastDone": 0.11, "changePercent": 4.76, "volume": 7200000, "strikePrice": 0.11, "expiryDate": "2028-12-21", "type": "call", "premium": -3.05, "leverage": 3.8}, {"symbol": "25318", "name": "SGPOMRT@EP2607B", "lastDone": 0.153, "changePercent": 4.79, "volume": 7000000, "strikePrice": 0.153, "expiryDate": "2026-07-28", "type": "call", "premium": 20.1, "leverage": 13.7}, {"symbol": "67914", "name": "SG#POMRTRC2608G", "lastDone": 0.113, "changePercent": -5.83, "volume": 6990000, "strikePrice": 0.113, "expiryDate": "2026-08-31", "type": "call", "premium": 0.33, "leverage": 3.7}, {"symbol": "18487", "name": "CIPOMRT@EC2609A", "lastDone": 0.045, "changePercent": -8.16, "volume": 6860000, "strikePrice": 0.045, "expiryDate": "2026-09-30", "type": "call", "premium": 30.01, "leverage": 9.3}, {"symbol": "22270", "name": "CIPOMRT@EC2604B", "lastDone": 0.019, "changePercent": -20.83, "volume": 6564000, "strikePrice": 0.019, "expiryDate": "2026-04-22", "type": "call", "premium": 34.46, "leverage": 110.3}, {"symbol": "23040", "name": "JPPOMRT@EP2605A", "lastDone": 0.1, "changePercent": 7.53, "volume": 6300000, "strikePrice": 0.1, "expiryDate": "2026-05-21", "type": "call", "premium": 14.7, "leverage": 21.0}, {"symbol": "16205", "name": "HSPOMRT@EP2604A", "lastDone": 0.204, "changePercent": 6.81, "volume": 6080000, "strikePrice": 0.204, "expiryDate": "2026-04-21", "type": "call", "premium": 4.81, "leverage": 10.3}, {"symbol": "25140", "name": "SGPOMRT@EC2606C", "lastDone": 0.044, "changePercent": -15.38, "volume": 5966000, "strikePrice": 0.044, "expiryDate": "2026-06-23", "type": "call", "premium": 48.13, "leverage": 47.6}, {"symbol": "24971", "name": "BPPOMRT@EP2607A", "lastDone": 0.088, "changePercent": 7.32, "volume": 5614000, "strikePrice": 0.088, "expiryDate": "2026-07-28", "type": "call", "premium": 26.48, "leverage": 23.8}, {"symbol": "25825", "name": "MSPOMRT@EP2612A", "lastDone": 0.183, "changePercent": 2.81, "volume": 5574000, "strikePrice": 0.183, "expiryDate": "2026-12-22", "type": "call", "premium": 29.58, "leverage": 11.5}, {"symbol": "23340", "name": "BIPOMRT@EP2607A", "lastDone": 0.092, "changePercent": 6.98, "volume": 5496000, "strikePrice": 0.092, "expiryDate": "2026-07-28", "type": "call", "premium": 26.71, "leverage": 22.8}, {"symbol": "13641", "name": "MBPOMRT@EP2604A", "lastDone": 0.16, "changePercent": 1.27, "volume": 5420000, "strikePrice": 0.16, "expiryDate": "2026-04-30", "type": "call", "premium": 7.45, "leverage": 13.1}, {"symbol": "23547", "name": "MSPOMRT@EC2606B", "lastDone": 0.058, "changePercent": -12.12, "volume": 5202000, "strikePrice": 0.058, "expiryDate": "2026-06-03", "type": "call", "premium": 34.06, "leverage": 36.1}, {"symbol": "23046", "name": "MSPOMRT@EP2606A", "lastDone": 0.105, "changePercent": 7.14, "volume": 5066000, "strikePrice": 0.105, "expiryDate": "2026-06-02", "type": "call", "premium": 16.27, "leverage": 20.0}, {"symbol": "23366", "name": "HSPOMRT@EC2606A", "lastDone": 0.042, "changePercent": -6.67, "volume": 5022000, "strikePrice": 0.042, "expiryDate": "2026-06-23", "type": "call", "premium": 48.03, "leverage": 49.9}, {"symbol": "20837", "name": "MSPOMRT@EC2610B", "lastDone": 0.031, "changePercent": -8.82, "volume": 4940000, "strikePrice": 0.031, "expiryDate": "2026-10-23", "type": "call", "premium": 45.31, "leverage": 13.5}, {"symbol": "17815", "name": "CTPOMRT@EC2610A", "lastDone": 0.028, "changePercent": -9.68, "volume": 4790000, "strikePrice": 0.028, "expiryDate": "2026-10-23", "type": "call", "premium": 52.71, "leverage": 15.0}, {"symbol": "22558", "name": "UBPOMRT@EP2607A", "lastDone": 0.087, "changePercent": 4.82, "volume": 4768000, "strikePrice": 0.087, "expiryDate": "2026-07-28", "type": "call", "premium": 26.47, "leverage": 24.1}, {"symbol": "23479", "name": "UBPOMRT@EC2605A", "lastDone": 0.095, "changePercent": -12.84, "volume": 4740000, "strikePrice": 0.095, "expiryDate": "2026-05-18", "type": "call", "premium": 19.09, "leverage": 22.1}, {"symbol": "25354", "name": "JPPOMRT@EP2607B", "lastDone": 0.148, "changePercent": 5.71, "volume": 4600000, "strikePrice": 0.148, "expiryDate": "2026-07-28", "type": "call", "premium": 19.86, "leverage": 14.2}, {"symbol": "68218", "name": "UB#POMRTRP2807B", "lastDone": 0.265, "changePercent": 1.92, "volume": 4580000, "strikePrice": 0.265, "expiryDate": "2028-07-26", "type": "call", "premium": -6.63, "leverage": 1.6}, {"symbol": "65829", "name": "HS#POMRTRP2812B", "lastDone": 0.093, "changePercent": 5.68, "volume": 4580000, "strikePrice": 0.093, "expiryDate": "2028-12-18", "type": "call", "premium": -2.34, "leverage": 4.5}, {"symbol": "22347", "name": "HSPOMRT@EP2608A", "lastDone": 0.094, "changePercent": 4.44, "volume": 4532000, "strikePrice": 0.094, "expiryDate": "2026-08-04", "type": "call", "premium": 26.76, "leverage": 22.3}, {"symbol": "23647", "name": "UBPOMRT@EC2606B", "lastDone": 0.096, "changePercent": -12.73, "volume": 4508000, "strikePrice": 0.096, "expiryDate": "2026-06-03", "type": "call", "premium": 23.95, "leverage": 21.8}, {"symbol": "25385", "name": "MSPOMRT@EP2607A", "lastDone": 0.147, "changePercent": 6.52, "volume": 4180000, "strikePrice": 0.147, "expiryDate": "2026-07-28", "type": "call", "premium": 19.81, "leverage": 14.3}, {"symbol": "66123", "name": "SG#POMRTRP2812V", "lastDone": 0.091, "changePercent": 3.41, "volume": 4170000, "strikePrice": 0.091, "expiryDate": "2028-12-28", "type": "call", "premium": -2.34, "leverage": 4.6}, {"symbol": "61449", "name": "JP#POMRTRC2606L", "lastDone": 0.093, "changePercent": -7.0, "volume": 4130000, "strikePrice": 0.093, "expiryDate": "2026-06-12", "type": "call", "premium": 0.91, "leverage": 4.5}, {"symbol": "17757", "name": "HSPOMRT@EC2610A", "lastDone": 0.034, "changePercent": 0, "volume": 4040000, "strikePrice": 0.034, "expiryDate": "2026-10-23", "type": "call", "premium": 45.99, "leverage": 12.3}, {"symbol": "63343", "name": "UB#POMRTRC2606C", "lastDone": 0.09, "changePercent": -7.22, "volume": 3900000, "strikePrice": 0.09, "expiryDate": "2026-06-22", "type": "call", "premium": 0.19, "leverage": 4.7}, {"symbol": "20470", "name": "HUPOMRT@EC2610A", "lastDone": 0.028, "changePercent": -9.68, "volume": 3820000, "strikePrice": 0.028, "expiryDate": "2026-10-23", "type": "call", "premium": 52.71, "leverage": 15.0}, {"symbol": "24972", "name": "DSPOMRT@EC2605A", "lastDone": 0.113, "changePercent": -9.6, "volume": 3740000, "strikePrice": 0.113, "expiryDate": "2026-05-18", "type": "call", "premium": 19.95, "leverage": 18.5}, {"symbol": "53012", "name": "UB#POMRTRP2812L", "lastDone": 0.051, "changePercent": 8.51, "volume": 3600000, "strikePrice": 0.051, "expiryDate": "2028-12-22", "type": "call", "premium": -0.91, "leverage": 8.2}, {"symbol": "21894", "name": "HSPOMRT@EC2604C", "lastDone": 0.027, "changePercent": -18.18, "volume": 3552000, "strikePrice": 0.027, "expiryDate": "2026-04-29", "type": "call", "premium": 34.84, "leverage": 77.6}, {"symbol": "24958", "name": "JPPOMRT@EP2605B", "lastDone": 0.065, "changePercent": 8.33, "volume": 3520000, "strikePrice": 0.065, "expiryDate": "2026-05-22", "type": "call", "premium": 18.23, "leverage": 32.2}, {"symbol": "22214", "name": "GJPOMRT@EC2604A", "lastDone": 0.01, "changePercent": 0, "volume": 3520000, "strikePrice": 0.01, "expiryDate": "2026-04-20", "type": "call", "premium": 37.98, "leverage": 209.6}, {"symbol": "21685", "name": "SGPOMRT@EC2609A", "lastDone": 0.044, "changePercent": -4.35, "volume": 3430000, "strikePrice": 0.044, "expiryDate": "2026-09-23", "type": "call", "premium": 29.87, "leverage": 9.5}, {"symbol": "67830", "name": "UB#POMRTRP2812K", "lastDone": 0.068, "changePercent": 9.68, "volume": 3350000, "strikePrice": 0.068, "expiryDate": "2028-12-14", "type": "call", "premium": -1.62, "leverage": 6.2}, {"symbol": "26091", "name": "JPPOMRT@EC2608A", "lastDone": 0.046, "changePercent": -9.8, "volume": 3200000, "strikePrice": 0.046, "expiryDate": "2026-08-17", "type": "call", "premium": 78.19, "leverage": 45.6}, {"symbol": "21323", "name": "BIPOMRT@EC2610B", "lastDone": 0.034, "changePercent": -8.11, "volume": 3200000, "strikePrice": 0.034, "expiryDate": "2026-10-23", "type": "call", "premium": 46.03, "leverage": 12.3}, {"symbol": "59683", "name": "UB#POMRTRC2608A", "lastDone": 0.056, "changePercent": -9.68, "volume": 3130000, "strikePrice": 0.056, "expiryDate": "2026-08-31", "type": "call", "premium": 0.67, "leverage": 7.5}, {"symbol": "21796", "name": "CTPOMRT@EC2609A", "lastDone": 0.043, "changePercent": -8.51, "volume": 3130000, "strikePrice": 0.043, "expiryDate": "2026-09-23", "type": "call", "premium": 29.49, "leverage": 9.7}, {"symbol": "23334", "name": "BPPOMRT@EC2607A", "lastDone": 0.053, "changePercent": -14.52, "volume": 3070000, "strikePrice": 0.053, "expiryDate": "2026-07-03", "type": "call", "premium": 48.52, "leverage": 39.5}, {"symbol": "54833", "name": "JP#POMRTRP2808R", "lastDone": 0.05, "changePercent": 6.38, "volume": 2940000, "strikePrice": 0.05, "expiryDate": "2028-08-11", "type": "call", "premium": -0.67, "leverage": 8.4}, {"symbol": "23513", "name": "HUPOMRT@EP2607B", "lastDone": 0.09, "changePercent": 4.65, "volume": 2714000, "strikePrice": 0.09, "expiryDate": "2026-07-28", "type": "call", "premium": 26.61, "leverage": 23.3}, {"symbol": "21930", "name": "BPPOMRT@EC2706A", "lastDone": 0.074, "changePercent": -3.9, "volume": 2700000, "strikePrice": 0.074, "expiryDate": "2027-06-23", "type": "call", "premium": 46.47, "leverage": 5.7}, {"symbol": "22298", "name": "HUPOMRT@EC2604B", "lastDone": 0.038, "changePercent": -20.83, "volume": 2644000, "strikePrice": 0.038, "expiryDate": "2026-04-24", "type": "call", "premium": 25.92, "leverage": 55.2}, {"symbol": "26798", "name": "JPPOMRT@EC2607A", "lastDone": 0.13, "changePercent": -9.09, "volume": 2600000, "strikePrice": 0.13, "expiryDate": "2026-07-24", "type": "call", "premium": 33.15, "leverage": 16.1}, {"symbol": "21869", "name": "BIPOMRT@EC2706A", "lastDone": 0.074, "changePercent": -6.33, "volume": 2600000, "strikePrice": 0.074, "expiryDate": "2027-06-23", "type": "call", "premium": 46.53, "leverage": 5.7}, {"symbol": "25131", "name": "JPPOMRT@EC2606C", "lastDone": 0.047, "changePercent": -14.55, "volume": 2524000, "strikePrice": 0.047, "expiryDate": "2026-06-23", "type": "call", "premium": 48.27, "leverage": 44.6}, {"symbol": "57323", "name": "SG#POMRTRC2608I", "lastDone": 0.132, "changePercent": -5.71, "volume": 2440000, "strikePrice": 0.132, "expiryDate": "2026-08-28", "type": "call", "premium": 0.1, "leverage": 3.2}]